cryptg_anylinux.libs/libgcc_s-a04fdf82.so.1
cryptg_anylinux-0.4.2.dist-info/WHEEL
cryptg_anylinux-0.4.2.dist-info/top_level.txt
cryptg_anylinux-0.4.2.dist-info/LICENSE.txt
cryptg_anylinux-0.4.2.dist-info/RECORD
cryptg_anylinux-0.4.2.dist-info/METADATA
cryptg/cryptg.cpython-310-x86_64-linux-gnu.so
cryptg/__init__.py
