Metadata-Version: 2.1
Name: cryptg-anylinux
Version: 0.4.2
Summary: Cryptographic utilities for Telegram.
Home-page: https://github.com/vanutp/cryptg-anylinux
Download-URL: https://github.com/vanutp/cryptg-anylinux/releases
Author: Dmitry D. Chernov; Lonami E
Author-email: blackdoomer@yandex.ru
License: CC0
Keywords: telegram crypto cryptography mtproto aes
Classifier: Development Status :: 4 - Beta
Classifier: Intended Audience :: Developers
Classifier: Topic :: Security :: Cryptography
Classifier: License :: CC0 1.0 Universal (CC0 1.0) Public Domain Dedication
Classifier: Programming Language :: Python :: 3
Classifier: Programming Language :: Python :: 3.7
Classifier: Programming Language :: Python :: 3.8
Classifier: Programming Language :: Python :: 3.9
Classifier: Programming Language :: Python :: 3.10
Classifier: Programming Language :: Python :: 3.11
Requires-Python: >=3.7
License-File: LICENSE.txt
